RPi.PIR-0.5.0.data/scripts/raspi-pir
raspi_pir/__init__.py
raspi_pir/main.py
raspi_pir/pir.py
RPi.PIR-0.5.0.dist-info/LICENSE
RPi.PIR-0.5.0.dist-info/METADATA
RPi.PIR-0.5.0.dist-info/WHEEL
RPi.PIR-0.5.0.dist-info/top_level.txt
RPi.PIR-0.5.0.dist-info/RECORD
